{
    "total": 336,
    "found": true,
    "result": [
        {
            "kind": [
                "n"
            ],
            "measure": null,
            "zhuyin": "ㄉㄢˋ",
            "_id": "4b0f735026304dbc480a5d04303f13f2",
            "type": "cnvi",
            "content": [
                {
                    "kind": "n",
                    "means": [
                        {
                            "mean": "đạn; viên đạn",
                            "explain": "(弹儿) 弹子",
                            "examples": [
                                {
                                    "m": "Ở đây có một viên đạn sắt.",
                                    "p_vn": "o day co mot vien dan sat.",
                                    "_id": "f2efc94449b26b3e2967bccbc95246e1",
                                    "id": 93946,
                                    "type": "e_cnvi",
                                    "e": "这里有一颗铁弹。",
                                    "p_cn": "zhe li youyi ke tie dan.",
                                    "p": "zhè li yǒuyī kē tiě dàn."
                                },
                                {
                                    "m": "Tháo đạn ra.",
                                    "p_vn": "thao dan ra.",
                                    "_id": "039d32e9621817310369c8ce97cb7a80",
                                    "id": 39791,
                                    "type": "e_cnvi",
                                    "e": "把子弹退出来。",
                                    "p_cn": "ba zidan tuichu lai。",
                                    "p": "bǎ zǐdàn tùichū lái。"
                                }
                            ]
                        },
                        {
                            "mean": "đạn; súng đạn; đạn pháo; bom",
                            "explain": "枪弹;炮弹;炸弹",
                            "examples": [
                                {
                                    "m": "Lựu đạn.",
                                    "p_vn": "luu dan.",
                                    "_id": "8599e98d945effc5cf91aeda9281a8ba",
                                    "id": 7066,
                                    "type": "e_cnvi",
                                    "e": "手榴弹。",
                                    "p_cn": "shouliudan",
                                    "p": "shǒulíudàn"
                                },
                                {
                                    "m": "Bom cháy; bom napan; bom lửa.",
                                    "p_vn": "bom chay; bom napan; bom lua.",
                                    "_id": "3af1419fa210d7ef0d83701d85577581",
                                    "id": 7067,
                                    "type": "e_cnvi",
                                    "e": "燃烧弹。",
                                    "p_cn": "ranshaodan",
                                    "p": "ránshāodàn"
                                },
                                {
                                    "m": "Anh ấy trúng đạn rồi.",
                                    "p_vn": "anh ay trung dan roi.",
                                    "_id": "f2efc94449b26b3e2967bccbc95254f9",
                                    "id": 93948,
                                    "type": "e_cnvi",
                                    "e": "他中弹了。",
                                    "p_cn": "ta zhong danle.",
                                    "p": "tā zhòng dànle."
                                },
                                {
                                    "m": "Anh ấy đang tập ném bom.",
                                    "p_vn": "anh ay dang tap nem bom.",
                                    "_id": "f2efc94449b26b3e2967bccbc9525bd3",
                                    "id": 93949,
                                    "type": "e_cnvi",
                                    "e": "他在练习投弹。",
                                    "p_cn": "ta zai lianxi toudan.",
                                    "p": "tā zài liànxí tóudàn."
                                },
                                {
                                    "m": "Bom nguyên tử.",
                                    "p_vn": "bom nguyen tu.",
                                    "_id": "f2efc94449b26b3e2967bccbc9527778",
                                    "id": 93953,
                                    "type": "e_cnvi",
                                    "e": "原子弹。",
                                    "p_cn": "yuanzidan.",
                                    "p": "yuánzǐdàn."
                                }
                            ]
                        }
                    ]
                }
            ],
            "popularity": {
                "notebook": 227,
                "search": 6225
            },
            "snym": null,
            "lv_hsk_new": "4, 5",
            "pinyin": "dàn",
            "cn_vi": "đạn.đàn",
            "word": "弹",
            "id": 11142,
            "phonetic": "dan",
            "rank": 1871,
            "lv_hsk": 4,
            "lv_tocfl": 4,
            "compound": "弹道 ; 弹弓 ; 弹夹 ; 弹尽粮绝 ; 弹尽援绝 ; 弹痕 ; 弹壳 ; 弹坑 ; 弹片 ; 弹体 ; 弹头 ; 弹丸 ; 弹丸之地 ; 弹无虚发 ; 弹药 ; 弹药库 ; 弹着点 ; 弹子 ; 弹子锁"
        },
        {
            "kind": [
                "v"
            ],
            "measure": null,
            "zhuyin": "ㄉㄢˋ",
            "_id": "6581b5ece9908d62be42e9af87905830",
            "type": "cnvi",
            "content": [
                {
                    "structs": [
                        {
                            "explain": "",
                            "examples": [
                                93994,
                                93995
                            ],
                            "struct": "弹 + 得/不 + 了/好/下去"
                        },
                        {
                            "explain": "",
                            "examples": [
                                93999,
                                93959
                            ],
                            "struct": "弹 + 开/上去/出去/回来/起来/到...."
                        },
                        {
                            "explain": "",
                            "examples": [
                                94006,
                                94007
                            ],
                            "struct": "弹 + 得/不 + 上去/起来。"
                        }
                    ],
                    "kind": "v",
                    "means": [
                        {
                            "mean": "bật;bắn; bắn ra",
                            "explain": "由于一物的弹性作用使另一物射出去",
                            "examples": [
                                {
                                    "m": "Máy phát bóng tự động có thể bắn bóng ra ngoài.",
                                    "p_vn": "may phat bong tu dong co the ban bong ra ngoai.",
                                    "_id": "f2efc94449b26b3e2967bccbc95290a1",
                                    "id": 93957,
                                    "type": "e_cnvi",
                                    "e": "自动发球机可以让求弹出去。",
                                    "p_cn": "zidong faqiu ji keyi rang qiu tanchu qu.",
                                    "p": "zìdòng fāqiú jī kěyǐ ràng qiú tánchū qù."
                                },
                                {
                                    "m": "Nắp bật ra ngoài rồi.",
                                    "p_vn": "nap bat ra ngoai roi.",
                                    "_id": "f2efc94449b26b3e2967bccbc95297d8",
                                    "id": 93959,
                                    "type": "e_cnvi",
                                    "e": "盖子弹开了。",
                                    "p_cn": "gai zitan kaile.",
                                    "p": "gài zǐtán kāile."
                                },
                                {
                                    "m": "Bóng bật đến tường rồi.",
                                    "p_vn": "bong bat den tuong roi.",
                                    "_id": "f2efc94449b26b3e2967bccbc9529b67",
                                    "id": 93960,
                                    "type": "e_cnvi",
                                    "e": "球弹到了墙上。",
                                    "p_cn": "qiu tan daole qiang shang.",
                                    "p": "qiú tán dàole qiáng shàng."
                                }
                            ]
                        },
                        {
                            "mean": "bật; xén; cắt",
                            "explain": "利用机械使纤维变得松软",
                            "examples": [
                                {
                                    "m": "Ba người công nhân đang bật bông.",
                                    "p_vn": "ba nguoi cong nhan dang bat bong.",
                                    "_id": "f2efc94449b26b3e2967bccbc952d9a9",
                                    "id": 93965,
                                    "type": "e_cnvi",
                                    "e": "三个工人在弹棉花。",
                                    "p_cn": "san ge gongren zai tan mianhua.",
                                    "p": "sān gè gōngrén zài tán miánhuā."
                                },
                                {
                                    "m": "Bố tôi đang xén lông cừu.",
                                    "p_vn": "bo toi dang xen long cuu.",
                                    "_id": "f2efc94449b26b3e2967bccbc952e9e3",
                                    "id": 93967,
                                    "type": "e_cnvi",
                                    "e": "我爸爸在弹羊毛。",
                                    "p_cn": "wo baba zai tan yangmao.",
                                    "p": "wǒ bàba zài tán yángmáo."
                                }
                            ]
                        },
                        {
                            "mean": "phủi; gạt",
                            "explain": "一个指头被另一个指头压住，然后用力挣开，借这个力量触物使动",
                            "examples": [
                                {
                                    "m": "Phủi bụi trên mũ đi.",
                                    "p_vn": "phui bui tren mu di.",
                                    "_id": "9eab74f316d7380c714cf056a63a5c2a",
                                    "id": 7074,
                                    "type": "e_cnvi",
                                    "e": "把帽子上的土弹去。",
                                    "p_cn": "ba maozi shang de tutan qu。",
                                    "p": "bǎ màozǐ shàng de tǔtán qù。"
                                },
                                {
                                    "m": "Anh ấy thích dùng tay gạt tàn thuốc.",
                                    "p_vn": "anh ay thich dung tay gat tan thuoc.",
                                    "_id": "f2efc94449b26b3e2967bccbc952f94b",
                                    "id": 93969,
                                    "type": "e_cnvi",
                                    "e": "他喜欢用手弹烟灰。",
                                    "p_cn": "ta xihuan yong shou tan yanhui.",
                                    "p": "tā xǐhuān yòng shǒu tán yānhuī."
                                }
                            ]
                        },
                        {
                            "mean": "gảy; đánh",
                            "explain": "用手指、器具拨弄或敲打，使物体振动",
                            "examples": [
                                {
                                    "m": "Em trai tôi thích đánh piano.",
                                    "p_vn": "em trai toi thich danh piano.",
                                    "_id": "f2efc94449b26b3e2967bccbc9531ffc",
                                    "id": 93973,
                                    "type": "e_cnvi",
                                    "e": "我弟弟喜欢弹钢琴。",
                                    "p_cn": "wo didi xihuan tan gangqin.",
                                    "p": "wǒ dìdì xǐhuān tán gāngqín."
                                },
                                {
                                    "m": "Tôi biết chơi ghi-ta.",
                                    "p_vn": "toi biet choi ghi-ta.",
                                    "_id": "f2efc94449b26b3e2967bccbc9533687",
                                    "id": 93976,
                                    "type": "e_cnvi",
                                    "e": "我会弹吉他。",
                                    "p_cn": "wo hui tan jita.",
                                    "p": "wǒ huì tán jítā."
                                },
                                {
                                    "m": "Cô ấy đang học đánh đàn tranh.",
                                    "p_vn": "co ay dang hoc danh dan tranh.",
                                    "_id": "f2efc94449b26b3e2967bccbc95c1a73",
                                    "id": 94065,
                                    "type": "e_cnvi",
                                    "e": "她在学弹古筝。",
                                    "p_cn": "ta zaixue tan guzheng.",
                                    "p": "tā zàixué tán gǔzhēng."
                                }
                            ]
                        },
                        {
                            "mean": "công kích",
                            "explain": "抨击",
                            "examples": [
                                {
                                    "m": "Anh ta dùng những lời độc ác để đả kích người khác.",
                                    "p_vn": "anh ta dung nhung loi doc ac de da kich nguoi khac.",
                                    "_id": "f2efc94449b26b3e2967bccbc95370de",
                                    "id": 93982,
                                    "type": "e_cnvi",
                                    "e": "他总是用恶言弹劾别人。",
                                    "p_cn": "ta zong shi yong e yan tanhe bieren.",
                                    "p": "tā zǒng shì yòng è yán tánhé biérén."
                                },
                                {
                                    "m": "Anh ấy luôn châm biếm khuyết điểm của người khác.",
                                    "p_vn": "anh ay luon cham biem khuyet diem cua nguoi khac.",
                                    "_id": "f2efc94449b26b3e2967bccbc953bd11",
                                    "id": 93991,
                                    "type": "e_cnvi",
                                    "e": "他总是讥弹别人的缺点。",
                                    "p_cn": "ta zong shi ji tan bieren de quedian.",
                                    "p": "tā zǒng shì jī tán biérén de quēdiǎn."
                                }
                            ]
                        }
                    ]
                }
            ],
            "popularity": {
                "notebook": 227,
                "search": 6225
            },
            "snym": null,
            "lv_hsk_new": "4, 5",
            "pinyin": "tán",
            "cn_vi": "đạn.đàn",
            "word": "弹",
            "id": 11143,
            "phonetic": "tan",
            "rank": 1872,
            "lv_tocfl": 4,
            "compound": "弹拨乐器 ; 弹唱 ; 弹词 ; 弹冠相庆 ; 弹劾 ; 弹簧 ; 弹簧秤 ; 弹簧门 ; 弹泪 ; 弹力 ; 弹射 ; 弹跳 ; 弹性 ; 弹压 ; 弹指"
        },
        {
            "measure": null,
            "zhuyin": "ㄈㄢˇㄉㄢˋㄉㄠˇㄉㄢˋ",
            "_id": "5cea162eb7ae4bd68d16dd1be0d04aee",
            "type": "cnvi",
            "content": [
                {
                    "kind": "n",
                    "means": [
                        {
                            "mean": "tên lửa chống tên lửa",
                            "explain": "antimissile missile",
                            "examples": []
                        }
                    ]
                }
            ],
            "popularity": {
                "notebook": 1,
                "search": 9
            },
            "snym": null,
            "cn_vi": "phản đạn đạo đạn",
            "pinyin": "fǎntán dǎodàn",
            "word": "反弹导弹",
            "id": 134062,
            "phonetic": "fantandaodan",
            "rank": 104816,
            "kind": [
                "n"
            ],
            "compound": null
        },
        {
            "kind": [
                "n"
            ],
            "measure": null,
            "topic": "18",
            "zhuyin": "ㄉㄢˋㄉㄠˋㄉㄠˇㄉㄢˋ",
            "_id": "3d8b3137a0ac77ae7785e2631fb2fc34",
            "type": "cnvi",
            "content": [
                {
                    "kind": "n",
                    "means": [
                        {
                            "mean": "Tên lửa đạn đạo",
                            "explain": "1） 按作战使用分为战略弹道导弹和战术弹道导弹。",
                            "examples": []
                        }
                    ]
                }
            ],
            "popularity": {
                "notebook": 1,
                "search": 14
            },
            "snym": null,
            "cn_vi": "đạn đạo đạo đạn",
            "pinyin": "dàndào dǎodàn",
            "word": "弹道导弹",
            "id": 81540,
            "phonetic": "dandaodaodan",
            "rank": 92409,
            "lv_tocfl": null,
            "compound": null
        },
        {
            "measure": null,
            "zhuyin": "ㄉㄢˋㄔㄨ",
            "_id": "f2c8c5fe5a6d4fe9a9eed98ef3694fb5",
            "type": "cnvi",
            "content": [
                {
                    "kind": "v",
                    "means": [
                        {
                            "mean": "đẩy ra",
                            "explain": "to eject",
                            "examples": []
                        },
                        {
                            "mean": "để thoát khỏi",
                            "explain": "to exit from",
                            "examples": []
                        },
                        {
                            "mean": "bật lên",
                            "explain": "to pop up",
                            "examples": [
                                {
                                    "m": "Tôi cài đặt thông báo đẩy cho điện thoại.",
                                    "p_vn": "toi cai dat thong bao day cho dien thoai.",
                                    "_id": "1c4b6fb8b4aa2c15606e08e617e5ac35",
                                    "id": 69161,
                                    "e": "我给手机设置了弹出通知。",
                                    "p_cn": "wǒ gěi shǒujī shezhile danchū tōngzhī.",
                                    "type": "e_cnvi",
                                    "p": "wǒ gěi shǒujī shèzhìle dànchū tōngzhī."
                                }
                            ]
                        }
                    ]
                }
            ],
            "popularity": {
                "notebook": 23,
                "search": 298
            },
            "snym": null,
            "cn_vi": "đạn xuất",
            "pinyin": "tán chū",
            "word": "弹出",
            "id": 96522,
            "phonetic": "danchu",
            "rank": 22274,
            "kind": [
                "v"
            ],
            "compound": null
        },
        {
            "measure": null,
            "zhuyin": "ㄊㄧㄠˋㄉㄢˋ",
            "_id": "d4d6d7432565429f971e086d8fddbea3",
            "type": "cnvi",
            "content": [
                {
                    "kind": "n",
                    "means": [
                        {
                            "mean": "ricochet",
                            "explain": "",
                            "examples": [
                                {
                                    "m": "Một ricochet đến đâu?",
                                    "p_vn": "Mot ricochet den dau?",
                                    "_id": "fe9302f201074c1e918db8fca011a528",
                                    "id": 58578,
                                    "type": "e_cnvi",
                                    "e": "跳弹从哪来的",
                                    "p_cn": "tiaodan cong nalai de",
                                    "p": "tiàodàn cóng nǎlái de"
                                }
                            ]
                        }
                    ]
                }
            ],
            "popularity": {
                "notebook": 0,
                "search": 6
            },
            "snym": null,
            "cn_vi": "khiêu đạn",
            "pinyin": "tiào dàn",
            "word": "跳弹",
            "id": 105666,
            "phonetic": "tiaodan",
            "rank": 115954,
            "kind": [
                "n"
            ],
            "compound": null
        },
        {
            "measure": null,
            "zhuyin": "ㄉㄢˋㄐㄧㄡ",
            "_id": "ccb740340af6479b8cec470b68ed788b",
            "type": "cnvi",
            "content": [
                {
                    "kind": "v",
                    "means": [
                        {
                            "mean": "buộc tội",
                            "explain": "to accuse",
                            "examples": []
                        },
                        {
                            "mean": "luận tội",
                            "explain": "to impeach",
                            "examples": []
                        }
                    ]
                }
            ],
            "popularity": {
                "notebook": 0,
                "search": 0
            },
            "snym": null,
            "cn_vi": "đạn củ",
            "pinyin": "dàn jiū",
            "word": "弹纠",
            "id": 96530,
            "phonetic": "danjiu",
            "rank": 158107,
            "kind": [
                "v"
            ],
            "compound": null
        },
        {
            "measure": null,
            "topic": "21",
            "zhuyin": "ㄉㄢˋㄇㄨˋ",
            "_id": "38616d69b19b4bc18c6f276d96066ae8",
            "type": "cnvi",
            "content": [
                {
                    "kind": "n",
                    "means": [
                        {
                            "mean": "bão bình luận; bão comment",
                            "explain": "",
                            "examples": []
                        },
                        {
                            "mean": "barrage (quân sự)",
                            "explain": "barrage (military)",
                            "examples": []
                        }
                    ]
                }
            ],
            "popularity": {
                "notebook": 40,
                "search": 699
            },
            "snym": null,
            "cn_vi": "đạn mạc",
            "pinyin": "dàn mù",
            "word": "弹幕",
            "id": 91259,
            "phonetic": "danmu",
            "rank": 12736,
            "kind": [
                "n"
            ],
            "compound": null
        },
        {
            "measure": null,
            "topic": "",
            "_id": "8cefb7da05384099a0cd05f6668756fd",
            "type": "cnvi",
            "content": [
                {
                    "kind": "n",
                    "means": [
                        {
                            "mean": "đánh bông",
                            "explain": "",
                            "examples": [
                                {
                                    "m": "cần bật bông.",
                                    "p_vn": "can bat bong.",
                                    "_id": "6986ba61cead1e708173d0801b0c1e6f",
                                    "id": 13942,
                                    "type": "e_cnvi",
                                    "e": "弹棉花的绷弓儿。",
                                    "p_cn": "tan mianhua de beng gong er.",
                                    "p": "tán miánhuā de bēng gōng er."
                                },
                                {
                                    "m": "bật bông; đánh bông.",
                                    "p_vn": "bat bong; danh bong.",
                                    "_id": "e61da779f141bd14f86a27e65a636c25",
                                    "id": 7072,
                                    "type": "e_cnvi",
                                    "e": "弹棉花",
                                    "p_cn": "tan mianhua",
                                    "p": "tán miánhuā"
                                }
                            ]
                        }
                    ]
                }
            ],
            "compare": null,
            "snym": null,
            "cn_vi": "đạn miên",
            "pinyin": "tán mián",
            "popularity": {
                "notebook": 0,
                "search": 2
            },
            "word": "弹棉",
            "id": 172638,
            "phonetic": "tanmian",
            "rank": 144727,
            "kind": [
                "n"
            ],
            "compound": null
        },
        {
            "measure": {
                "pinyin": "Gè, méi, kē",
                "examples": "这个炸弹可以炸死很多人。\nZhège zhàdàn kěyǐ zhà sǐ hěnduō rén.\nQuả bom này có thể giết chết nhiều người.",
                "measure": "个, 枚, 颗"
            },
            "topic": "6, 18, 27, 43, 54",
            "zhuyin": "ㄓㄚˋㄉㄢˋ",
            "_id": "073c7dc6d890d85edbcdacc544e92120",
            "type": "cnvi",
            "content": [
                {
                    "kind": "n",
                    "means": [
                        {
                            "mean": "bom; trái phá",
                            "explain": "一种爆炸性武器，通常外壳用铁制成，里面装有炸药，触动信管就爆炸一般用飞机投掷",
                            "examples": [
                                {
                                    "m": "Khi quả bom nổ ở quán cà phê",
                                    "p_vn": "khi qua bom no o quan ca phe",
                                    "_id": "2829e3e4d5c3490a9b659e0bd953f3b7",
                                    "id": 66330,
                                    "type": "e_cnvi",
                                    "e": "当炸弹在咖啡店爆炸时",
                                    "p_cn": "dang zhadan zai kafeidian baozha shi",
                                    "p": "dāng zhàdàn zài kāfēidiàn bàozhà shí"
                                },
                                {
                                    "m": "Ludd nhận công lao cho một vụ đánh bom xe hơi",
                                    "p_vn": "Ludd nhan cong lao cho mot vu danh bom xe hoi",
                                    "_id": "4b8cb20ce31d45ccba0fc1f83929e3e8",
                                    "id": 62364,
                                    "type": "e_cnvi",
                                    "e": "拉德党策划了一起汽车炸弹事件",
                                    "p_cn": "lade dang cehua le yiqi qiche zhadan shijian",
                                    "p": "lādé dǎng cèhuá le yīqǐ qìchē zhàdàn shìjiàn"
                                },
                                {
                                    "m": "Các mảnh vỡ và các nhân chứng cho biết nó trông giống như một quả bom.",
                                    "p_vn": "Cac manh vo va cac nhan chung cho biet no trong giong nhu mot qua bom.",
                                    "_id": "52e090f91bfe4bbbbe1c32749d3bad2a",
                                    "id": 59686,
                                    "type": "e_cnvi",
                                    "e": "残骸和目击者证明似乎是炸弹",
                                    "p_cn": "canhai he mujizhe zhengming sihu shi zhadan",
                                    "p": "cánhái hé mùjízhě zhèngmíng sìhū shì zhàdàn"
                                },
                                {
                                    "m": "Trông giống như kết quả của một vụ đánh bom xe hơi.",
                                    "p_vn": "Trong giong nhu ket qua cua mot vu danh bom xe hoi.",
                                    "_id": "5e05c6a4c1814653ad1c2a83a70584b1",
                                    "id": 62362,
                                    "type": "e_cnvi",
                                    "e": "像是汽车炸弹爆炸之后的样子",
                                    "p_cn": "xiangshi qiche zhadan baozha zhihou de yangzi",
                                    "p": "xiàngshì qìchē zhàdàn bàozhà zhīhòu de yángzǐ"
                                },
                                {
                                    "m": "Đó là lý do tại sao mẹ tôi chết trong vụ đánh bom xe đó.",
                                    "p_vn": "do la ly do tai sao me toi chet trong vu danh bom xe do.",
                                    "_id": "6e3fef3be58e483f8e0080850db6eb57",
                                    "id": 62363,
                                    "type": "e_cnvi",
                                    "e": "所以我妈妈被汽车炸弹害死了",
                                    "p_cn": "suoyi wo mama bei qiche zhadan haisi le",
                                    "p": "suǒyǐ wǒ māma bèi qìchē zhàdàn hàisǐ le"
                                }
                            ]
                        },
                        {
                            "mean": "đạn pháo",
                            "explain": "用炮来发射的弹药, 通常由弹头、药筒、引信、发射药、底火等部分构成, 弹头能爆炸按用途分为穿甲弹、爆破弹、燃烧弹、烟幕弹等有时专指弹头; 用枪发射的弹药, 由药筒、底火、发射药、弹头构成",
                            "examples": []
                        }
                    ]
                }
            ],
            "popularity": {
                "notebook": 57,
                "search": 729
            },
            "snym": null,
            "lv_hsk_new": "6, 7-9",
            "pinyin": "zhàdàn",
            "cn_vi": "tạc đạn",
            "word": "炸弹",
            "id": 63183,
            "phonetic": "zhadan",
            "rank": 12362,
            "kind": [
                "n"
            ],
            "compound": null
        },
        {
            "measure": null,
            "zhuyin": "ㄉㄢˋㄏㄨㄚ",
            "_id": "9d6c1be8daec402f8f90e60d4e850729",
            "type": "cnvi",
            "content": [
                {
                    "kind": "n",
                    "means": [
                        {
                            "mean": "để làm mềm sợi bông bằng cách đánh lông tơ",
                            "explain": "to soften cotton fiber by fluffing",
                            "examples": []
                        }
                    ]
                }
            ],
            "popularity": {
                "notebook": 0,
                "search": 2
            },
            "snym": null,
            "cn_vi": "đạn hoa",
            "pinyin": "tán huā",
            "word": "弹花",
            "id": 96532,
            "phonetic": "tanhua",
            "rank": 142303,
            "kind": [
                "n"
            ],
            "compound": null
        },
        {
            "measure": null,
            "zhuyin": "ㄐㄧㄡㄉㄢˋ",
            "_id": "174bdd1df63f4bc3a291f4485d35f0a1",
            "type": "cnvi",
            "content": [
                {
                    "kind": "v",
                    "means": [
                        {
                            "mean": "để kiểm duyệt",
                            "explain": "to censure",
                            "examples": []
                        },
                        {
                            "mean": "tố cáo",
                            "explain": "to denounce",
                            "examples": []
                        },
                        {
                            "mean": "luận tội",
                            "explain": "to impeach",
                            "examples": []
                        }
                    ]
                }
            ],
            "popularity": {
                "notebook": 0,
                "search": 6
            },
            "snym": null,
            "cn_vi": "củ đạn",
            "pinyin": "jiū tán",
            "word": "纠弹",
            "id": 99097,
            "phonetic": "jiutan",
            "rank": 116318,
            "kind": [
                "v"
            ],
            "compound": null
        },
        {
            "measure": {
                "pinyin": "Méi",
                "examples": "导弹已偏离轨道。\nDǎodàn yǐ piānlí guǐdào.\nTên lửa bị lệch khỏi quỹ đạo của nó.",
                "measure": "枚"
            },
            "topic": "18",
            "zhuyin": "ㄉㄠˇㄉㄢˋ",
            "_id": "7cda38ab0d951feda15a37fb099a1678",
            "type": "cnvi",
            "content": [
                {
                    "kind": "n",
                    "means": [
                        {
                            "mean": "đạn đạo; hoả tiễn; tên lửa đạn đạo; đạo đạn",
                            "explain": "装有弹头和动力装置并能制导的高速飞行武器依靠控制系统制导，能使弹头击中预定目标种类很多，可以从地面上、舰艇上或飞机上发射出去，轰击地面、海上或空中的目标",
                            "examples": [
                                {
                                    "m": "đạn đạo tầm ngắn",
                                    "p_vn": "dan dao tam ngan",
                                    "_id": "042414cdb8c3720f0f94da68c45173a5",
                                    "id": 9504,
                                    "type": "e_cnvi",
                                    "e": "短程导弹",
                                    "p_cn": "duancheng daodan",
                                    "p": "duǎnchéng dǎodàn"
                                },
                                {
                                    "m": "Anh ấy là cựu nhà điều hành tên lửa quân đội",
                                    "p_vn": "Anh ay la cuu nha dieu hanh ten lua quan doi",
                                    "_id": "a3c6de07e0814f3f9bbceb6603a30573",
                                    "id": 61231,
                                    "type": "e_cnvi",
                                    "e": "他是前陆军导弹操作员",
                                    "p_cn": "ta shi qian lujun daodan caozuoyuan",
                                    "p": "tā shì qián lùjūn dǎodàn cāozuòyuán"
                                },
                                {
                                    "m": "tên lửa tầm xa.",
                                    "p_vn": "ten lua tam xa",
                                    "_id": "b5eb28b6205650fb7799cdd186a89ddd",
                                    "id": 47628,
                                    "type": "e_cnvi",
                                    "e": "远程导弹。",
                                    "p_cn": "yuancheng daodan",
                                    "p": "yuǎnchéng dǎodàn。"
                                }
                            ]
                        }
                    ]
                }
            ],
            "popularity": {
                "notebook": 43,
                "search": 342
            },
            "snym": null,
            "cn_vi": "đạo đạn",
            "pinyin": "dǎodàn",
            "lv_hsk_new": "6",
            "word": "导弹",
            "id": 11455,
            "phonetic": "daodan",
            "rank": 20327,
            "kind": [
                "n"
            ],
            "compound": null
        },
        {
            "kind": [
                "n"
            ],
            "measure": null,
            "topic": "21, 44",
            "zhuyin": "ㄉㄢˋㄏㄨㄤˊ",
            "_id": "32973a04788fce004546f74106f263d8",
            "type": "cnvi",
            "content": [
                {
                    "kind": "n",
                    "means": [
                        {
                            "mean": "lò xo",
                            "explain": "利用材料的弹性作用制成的零件，在外力作用下能发生形变，除去外力后又恢复原状常见的用合金钢制成，有螺旋形、板形等不同形状有的地区叫绷簧",
                            "examples": [
                                {
                                    "m": "lò xo giảm xóc",
                                    "p_vn": "lo xo giam xoc",
                                    "_id": "4396b81e475abc66d790071eb7e968d8",
                                    "id": 41259,
                                    "type": "e_cnvi",
                                    "e": "弹簧吸收震动",
                                    "p_cn": "tanhuang xishou zhendong",
                                    "p": "tánhuáng xīshōu zhèndòng"
                                },
                                {
                                    "m": "Lò xo bật văng đi rồi",
                                    "p_vn": "lo xo bat vang di roi",
                                    "_id": "91dd83a6369ad4acad6e6d819b11a1e3",
                                    "id": 1444,
                                    "type": "e_cnvi",
                                    "e": "弹簧绷飞了。",
                                    "p_cn": "tanhuang beng feile.",
                                    "p": "tánhuáng bēng fēile."
                                },
                                {
                                    "m": "Cái đệm giường lò xo cũ quá rồi, lúc nào cũng kêu cót két.",
                                    "p_vn": "cai dem giuong lo xo cu qua roi, luc nao cung keu cot ket.",
                                    "_id": "c0fb569df3556ccddfe6404866e86a34",
                                    "id": 88554,
                                    "type": "e_cnvi",
                                    "e": "床的弹簧太旧了，总是发出咯吱声。",
                                    "p_cn": "chuang de tanhuang tai jiule, zong shi fachu ge zi sheng.",
                                    "p": "chuáng de tánhuáng tài jiùle, zǒng shì fāchū gē zī shēng."
                                }
                            ]
                        }
                    ]
                }
            ],
            "popularity": {
                "notebook": 135,
                "search": 1083
            },
            "snym": null,
            "cn_vi": "đạn hoàng",
            "pinyin": "tánhuáng",
            "word": "弹簧",
            "id": 11152,
            "phonetic": "tanhuang",
            "rank": 9226,
            "lv_tocfl": null,
            "compound": null
        },
        {
            "measure": null,
            "topic": "",
            "_id": "119c107cc1714bae9dc664535f92f939",
            "type": "cnvi",
            "content": [
                {
                    "kind": "n",
                    "means": [
                        {
                            "mean": "đuôi đạn",
                            "explain": "",
                            "examples": []
                        }
                    ]
                }
            ],
            "compare": null,
            "snym": null,
            "cn_vi": "đạn vĩ",
            "pinyin": "dàn wěi",
            "popularity": {
                "notebook": 0,
                "search": 0
            },
            "word": "弹尾",
            "id": 180323,
            "phonetic": "danwei",
            "rank": 158107,
            "kind": [
                "n"
            ],
            "compound": null
        },
        {
            "measure": null,
            "topic": "",
            "_id": "717cdd61b97b4a7fafb6788ee76da8b3",
            "type": "cnvi",
            "content": [
                {
                    "kind": "n",
                    "means": [
                        {
                            "mean": "đạn chì",
                            "explain": "",
                            "examples": []
                        }
                    ]
                }
            ],
            "compare": null,
            "snym": null,
            "cn_vi": "duyên đạn",
            "pinyin": "qiān dàn",
            "popularity": {
                "notebook": 0,
                "search": 0
            },
            "word": "铅弹",
            "id": 179315,
            "phonetic": "qiandan",
            "rank": 158107,
            "kind": [
                "n"
            ],
            "compound": null
        },
        {
            "measure": null,
            "topic": "",
            "_id": "95f295547ec7406185c0cf4f1826e28d",
            "type": "cnvi",
            "content": [
                {
                    "kind": "n",
                    "means": [
                        {
                            "mean": "viên đạn",
                            "explain": "",
                            "examples": []
                        }
                    ]
                }
            ],
            "compare": null,
            "snym": null,
            "cn_vi": "đạn nhi",
            "pinyin": "dàn er",
            "popularity": {
                "notebook": 0,
                "search": 0
            },
            "word": "弹儿",
            "id": 183044,
            "phonetic": "daner",
            "rank": 158107,
            "kind": [
                "n"
            ],
            "compound": null
        },
        {
            "kind": [
                "n"
            ],
            "measure": null,
            "zhuyin": "ㄉㄢˋㄎㄜˊ",
            "_id": "1c06e7f1752f764bebc3ffa5ca27cc02",
            "type": "cnvi",
            "content": [
                {
                    "kind": "n",
                    "means": [
                        {
                            "mean": "vỏ đạn; các-tút",
                            "explain": "药筒的通称",
                            "examples": [
                                {
                                    "m": "vỏ đạn.",
                                    "p_vn": "vo dan.",
                                    "_id": "d0100feb6df5a1fe0454a1f16fe3e32e",
                                    "id": 23260,
                                    "type": "e_cnvi",
                                    "e": "子弹壳儿。",
                                    "p_cn": "zǐdanke er。",
                                    "p": "zǐdànké ér。"
                                }
                            ]
                        },
                        {
                            "mean": "vỏ bom",
                            "explain": "炸弹的外壳",
                            "examples": []
                        }
                    ]
                }
            ],
            "popularity": {
                "notebook": 3,
                "search": 26
            },
            "snym": null,
            "cn_vi": "đạn xác",
            "pinyin": "dànké",
            "word": "弹壳",
            "id": 11159,
            "phonetic": "danke",
            "rank": 75738,
            "lv_tocfl": null,
            "compound": null
        },
        {
            "kind": [
                "n"
            ],
            "measure": null,
            "zhuyin": "ㄊㄤˊㄉㄢˋ",
            "_id": "35196defa782955a84cb93d4a4b27dd3",
            "type": "cnvi",
            "content": [
                {
                    "kind": "n",
                    "means": [
                        {
                            "mean": "đạn bọc đường; mật ngọt chết ruồi",
                            "explain": "糖衣炮弹的简称",
                            "examples": []
                        }
                    ]
                }
            ],
            "popularity": {
                "notebook": 2,
                "search": 14
            },
            "snym": null,
            "cn_vi": "đường đạn",
            "pinyin": "táng dàn",
            "word": "糖弹",
            "id": 50019,
            "phonetic": "tangdan",
            "rank": 92678,
            "lv_tocfl": null,
            "compound": null
        },
        {
            "kind": [
                "n"
            ],
            "measure": null,
            "zhuyin": "ㄔㄡˋㄉㄢˋ",
            "_id": "137fc7a3f586d84c635856b6efcd1a2b",
            "type": "cnvi",
            "content": [
                {
                    "kind": "n",
                    "means": [
                        {
                            "mean": "đạn lép; pháo điếc; pháo lép",
                            "explain": "失效打不响的炮弹",
                            "examples": []
                        }
                    ]
                }
            ],
            "popularity": {
                "notebook": 1,
                "search": 4
            },
            "snym": null,
            "cn_vi": "xú đạn",
            "pinyin": "chòu dàn",
            "word": "臭弹",
            "id": 8162,
            "phonetic": "choudan",
            "rank": 128490,
            "lv_tocfl": null,
            "compound": null
        },
        {
            "kind": [
                "n"
            ],
            "measure": null,
            "zhuyin": "ㄉㄢˋㄘˊ",
            "_id": "1299c341bf5a7add2937df4da3ce913e",
            "type": "cnvi",
            "content": [
                {
                    "kind": "n",
                    "means": [
                        {
                            "mean": "đàn từ (một hình thức văn nghệ dân gian, lưu hành ở các tỉnh miền nam, Trung Quốc.)",
                            "explain": "曲艺的一种，流行于南方各省，有说有唱，曲调、唱腔各地不同，用三弦伴奏，或再加琵琶陪衬也指说唱弹词的底本",
                            "examples": []
                        }
                    ]
                }
            ],
            "popularity": {
                "notebook": 1,
                "search": 44
            },
            "snym": null,
            "cn_vi": "đạn từ",
            "pinyin": "táncí",
            "word": "弹词",
            "id": 11146,
            "phonetic": "tanci",
            "rank": 61072,
            "lv_tocfl": null,
            "compound": null
        },
        {
            "measure": null,
            "zhuyin": "ㄉㄢˋㄧㄚˊ",
            "_id": "0a841c97255048cab921366730d5e5bd",
            "type": "cnvi",
            "content": [
                {
                    "kind": "n",
                    "means": [
                        {
                            "mean": "al dente",
                            "explain": "",
                            "examples": []
                        }
                    ]
                }
            ],
            "popularity": {
                "notebook": 0,
                "search": 34
            },
            "snym": null,
            "cn_vi": "đạn nha",
            "pinyin": "dàn yá",
            "word": "弹牙",
            "id": 91261,
            "phonetic": "danya",
            "rank": 67868,
            "kind": [
                "n"
            ],
            "compound": null
        },
        {
            "kind": [
                "n"
            ],
            "measure": null,
            "zhuyin": "ㄏㄜˊㄉㄢˋ",
            "_id": "2da9fef8bbecdbf93e3868721b381373",
            "type": "cnvi",
            "content": [
                {
                    "kind": "n",
                    "means": [
                        {
                            "mean": "đạn hạt nhân",
                            "explain": "原子弹、氢弹等原子武器的统称",
                            "examples": []
                        }
                    ]
                }
            ],
            "popularity": {
                "notebook": 6,
                "search": 115
            },
            "snym": null,
            "cn_vi": "hạch đạn",
            "pinyin": "hédàn",
            "word": "核弹",
            "id": 23143,
            "phonetic": "hedan",
            "rank": 38589,
            "lv_tocfl": null,
            "compound": null
        },
        {
            "kind": [
                "n"
            ],
            "measure": null,
            "zhuyin": "ㄉㄢˋㄐㄧㄚ",
            "_id": "2e8a2a8803ec3aed363dfc494818adc5",
            "type": "cnvi",
            "content": [
                {
                    "kind": "n",
                    "means": [
                        {
                            "mean": "đồ sạc; máy sạc",
                            "explain": "夹子弹用的长条夹用来将子弹成排夹住，以便压入弹匣",
                            "examples": []
                        }
                    ]
                }
            ],
            "popularity": {
                "notebook": 3,
                "search": 82
            },
            "snym": null,
            "cn_vi": "đạn giáp",
            "pinyin": "dàn jiá",
            "word": "弹夹",
            "id": 11156,
            "phonetic": "danjia",
            "rank": 45864,
            "lv_tocfl": null,
            "compound": null
        },
        {
            "measure": null,
            "zhuyin": "ㄑㄧㄡˊㄉㄢˋ",
            "_id": "7873f2ff3cba4101ba9ffc2de1ae368d",
            "type": "cnvi",
            "content": [
                {
                    "kind": "n",
                    "means": [
                        {
                            "mean": "bóng (trong thể thao, bao gồm bida)",
                            "explain": "ball (in sport, incl. billiards)",
                            "examples": []
                        }
                    ]
                }
            ],
            "popularity": {
                "notebook": 1,
                "search": 63
            },
            "snym": null,
            "cn_vi": "cầu đạn",
            "pinyin": "qiú dàn",
            "word": "球弹",
            "id": 98496,
            "phonetic": "qiudan",
            "rank": 52068,
            "kind": [
                "n"
            ],
            "compound": null
        },
        {
            "kind": [
                "n"
            ],
            "measure": null,
            "zhuyin": "ㄉㄢˋㄍㄨㄥ",
            "_id": "2a8bc1962635b1d4f0adb58162bfb0e5",
            "type": "cnvi",
            "content": [
                {
                    "kind": "n",
                    "means": [
                        {
                            "mean": "cung; cây cung; ná; giàn ná; giàn thun (để bắn đạn); ná thung",
                            "explain": "用弹力发射弹丸的弓，古代用做武器，现在有时用来打鸟",
                            "examples": []
                        }
                    ]
                }
            ],
            "popularity": {
                "notebook": 13,
                "search": 141
            },
            "snym": null,
            "cn_vi": "đạn cung",
            "pinyin": "dàngōng",
            "word": "弹弓",
            "id": 11148,
            "phonetic": "dangong",
            "rank": 34672,
            "lv_tocfl": null,
            "compound": null
        },
        {
            "measure": null,
            "zhuyin": "ㄙㄢˋㄉㄢˋ",
            "_id": "a5c99139ce074095a9230efe604a739c",
            "type": "cnvi",
            "content": [
                {
                    "kind": "n",
                    "means": [
                        {
                            "mean": "(súng) bắn",
                            "explain": "(gun) shot",
                            "examples": []
                        },
                        {
                            "mean": "bắn ống",
                            "explain": "canister shot",
                            "examples": []
                        }
                    ]
                }
            ],
            "popularity": {
                "notebook": 0,
                "search": 12
            },
            "snym": null,
            "cn_vi": "tán đạn",
            "pinyin": "sàn dàn",
            "word": "散弹",
            "id": 97134,
            "phonetic": "sandan",
            "rank": 98387,
            "kind": [
                "n"
            ],
            "compound": null
        },
        {
            "kind": [
                "n"
            ],
            "measure": null,
            "zhuyin": "ㄉㄢˋㄊㄡˊ",
            "_id": "da3c744ae32c8fb54f7c2d844a86ac83",
            "type": "cnvi",
            "content": [
                {
                    "kind": "n",
                    "means": [
                        {
                            "mean": "đầu đạn",
                            "explain": "枪弹、炮弹、导弹等的前部，射出后能起杀伤或破坏作用",
                            "examples": []
                        }
                    ]
                }
            ],
            "popularity": {
                "notebook": 4,
                "search": 19
            },
            "snym": null,
            "cn_vi": "đạn đầu",
            "pinyin": "dàntóu",
            "word": "弹头",
            "id": 11167,
            "phonetic": "dantou",
            "rank": 84303,
            "lv_tocfl": null,
            "compound": null
        },
        {
            "kind": [
                "v"
            ],
            "measure": null,
            "zhuyin": "ㄉㄢˋㄌㄟˋ",
            "_id": "edd0f24a24bedf841256a6a68b364fe1",
            "type": "cnvi",
            "content": [
                {
                    "kind": "v",
                    "means": [
                        {
                            "mean": "gạt nước mắt; nước mắt thương tâm",
                            "explain": "挥泪，泛指伤心流泪",
                            "examples": []
                        }
                    ]
                }
            ],
            "popularity": {
                "notebook": 0,
                "search": 2
            },
            "snym": null,
            "cn_vi": "đạn lệ",
            "pinyin": "tán lèi",
            "word": "弹泪",
            "id": 11161,
            "phonetic": "tanlei",
            "rank": 139907,
            "lv_tocfl": null,
            "compound": null
        },
        {
            "kind": [
                "n"
            ],
            "measure": null,
            "zhuyin": "ㄉㄢˋㄨㄢˊ",
            "_id": "e4b32631c3f89737dbd7345e3447bc9e",
            "type": "cnvi",
            "content": [
                {
                    "kind": "n",
                    "means": [
                        {
                            "mean": "viên đạn",
                            "explain": "弹弓所用的铁丸或泥丸",
                            "examples": []
                        },
                        {
                            "mean": "đầu đạn",
                            "explain": "枪弹的弹头",
                            "examples": []
                        },
                        {
                            "mean": "chật hẹp nhỏ bé; nơi chật hẹp nhỏ bé",
                            "explain": "比喻地方狭小",
                            "examples": [
                                {
                                    "m": "nơi chật hẹp nhỏ bé",
                                    "p_vn": "noi chat hep nho be",
                                    "_id": "25f2313ab598b37d19a1bd26f43d296d",
                                    "id": 7084,
                                    "type": "e_cnvi",
                                    "e": "弹丸之地",
                                    "p_cn": "danwan zhi di",
                                    "p": "dànwánzhīdì"
                                }
                            ]
                        }
                    ]
                }
            ],
            "popularity": {
                "notebook": 8,
                "search": 66
            },
            "snym": {
                "anto": [
                    "广漠"
                ]
            },
            "cn_vi": "đạn hoàn",
            "pinyin": "dànwán",
            "word": "弹丸",
            "id": 11168,
            "phonetic": "danwan",
            "rank": 51013,
            "lv_tocfl": null,
            "compound": null
        },
        {
            "kind": [
                "n"
            ],
            "measure": null,
            "topic": "18",
            "zhuyin": "ㄑㄧㄤㄉㄢˋ",
            "_id": "e0f8cdb90d2cf92bf96ef7ebbe4e95da",
            "type": "cnvi",
            "content": [
                {
                    "kind": "n",
                    "means": [
                        {
                            "mean": "đạn",
                            "explain": "用枪发射的弹药，由药筒、底火、发射药、弹头构成有时专指弹头俗称子弹",
                            "examples": [
                                {
                                    "m": "tiếng đạn rít",
                                    "p_vn": "tieng dan rit",
                                    "_id": "4f673fe0d88c17a66f8467d978554307",
                                    "id": 42452,
                                    "type": "e_cnvi",
                                    "e": "枪弹的啸声。",
                                    "p_cn": "qiangdan de xiao sheng",
                                    "p": "qiāngdàn de xiàoshēng。"
                                }
                            ]
                        },
                        {
                            "mean": "bom",
                            "explain": "一种爆炸性武器, 通常外壳用铁制成, 里面装有炸药, 触动信管就爆炸一般用飞机投掷",
                            "examples": []
                        }
                    ]
                }
            ],
            "popularity": {
                "notebook": 4,
                "search": 36
            },
            "snym": {
                "syno": [
                    "子弹"
                ]
            },
            "cn_vi": "thương đạn",
            "pinyin": "qiāngdàn",
            "word": "枪弹",
            "id": 42569,
            "phonetic": "qiangdan",
            "rank": 66632,
            "lv_tocfl": null,
            "compound": null
        },
        {
            "measure": null,
            "zhuyin": "ㄕˊㄉㄢˋ",
            "_id": "deb41c248b724ce78c1ec3e45ac7b57d",
            "type": "cnvi",
            "content": [
                {
                    "kind": "n",
                    "means": [
                        {
                            "mean": "đạn thật",
                            "explain": "live ammunition",
                            "examples": [
                                {
                                    "m": "diễn tập bắn đạn thật",
                                    "p_vn": "dien tap ban dan that",
                                    "_id": "81f962ffd7ddf5ab303b261613e280bc",
                                    "id": 44141,
                                    "type": "e_cnvi",
                                    "e": "实弹演习",
                                    "p_cn": "shidan yanxi",
                                    "p": "shídànyǎnxí"
                                },
                                {
                                    "m": "súng vác vai, đạn lên nòng",
                                    "p_vn": "sung vac vai, dan len nong",
                                    "_id": "9a410e86199f3c4f620da8fff80f8a8b",
                                    "id": 16861,
                                    "type": "e_cnvi",
                                    "e": "荷枪实弹",
                                    "p_cn": "heqiāngshidan",
                                    "p": "hèqiāngshídàn"
                                }
                            ]
                        }
                    ]
                }
            ],
            "popularity": {
                "notebook": 3,
                "search": 27
            },
            "snym": null,
            "cn_vi": "thực đạn",
            "pinyin": "shídàn",
            "word": "实弹",
            "id": 96138,
            "phonetic": "shidan",
            "rank": 74191,
            "kind": [
                "n"
            ],
            "compound": null
        },
        {
            "kind": [
                "v"
            ],
            "measure": null,
            "zhuyin": "ㄆㄥㄉㄢˋ",
            "_id": "c0a1c3c1b5c5eebc70669a24339cbeef",
            "type": "cnvi",
            "content": [
                {
                    "kind": "v",
                    "means": [
                        {
                            "mean": "công kích; đả kích; phê phán",
                            "explain": "抨击",
                            "examples": []
                        }
                    ]
                }
            ],
            "popularity": {
                "notebook": 1,
                "search": 2
            },
            "snym": null,
            "cn_vi": "phanh đạn",
            "pinyin": "pēng tán",
            "word": "抨弹",
            "id": 40559,
            "phonetic": "pengtan",
            "rank": 144906,
            "lv_tocfl": null,
            "compound": null
        },
        {
            "kind": [
                "n",
                "adj"
            ],
            "measure": null,
            "zhuyin": "ㄉㄢˋㄒㄧㄥˋ",
            "_id": "814302ef36a2eaa4ee69d1460269f3a6",
            "type": "cnvi",
            "content": [
                {
                    "kind": "n",
                    "means": [
                        {
                            "mean": "tính đàn hồi; đàn tính",
                            "explain": "物体受外力作用时产生形变，外力消失后能恢复原状的性能",
                            "examples": [
                                {
                                    "m": "Sợi dây chun này có tính đàn hồi rất tốt.",
                                    "p_vn": "soi day chun nay co tinh dan hoi rat tot.",
                                    "_id": "ac4bbc5f882264acadd04ccb5cc74e1c",
                                    "id": 136303,
                                    "type": "e_cnvi",
                                    "e": "这个橡皮筋有很好的弹性。",
                                    "p_cn": "zhege xiangpi jin you hen hao de tanxing.",
                                    "p": "zhègè xiàngpí jīn yǒu hěn hǎo de tánxìng."
                                },
                                {
                                    "m": "Quả bóng da có tính đàn hồi rất tốt.",
                                    "p_vn": "qua bong da co tinh dan hoi rat tot.",
                                    "_id": "ac4bbc5f882264acadd04ccb5cc757ee",
                                    "id": 136304,
                                    "type": "e_cnvi",
                                    "e": "皮球的弹性非常好。",
                                    "p_cn": "piqiu de tanxing feichang hao.",
                                    "p": "píqiú de tánxìng fēicháng hǎo."
                                },
                                {
                                    "m": "Tôi thích dùng văn phòng phẩm có tính đàn hồi tốt.",
                                    "p_vn": "toi thich dung van phong pham co tinh dan hoi tot.",
                                    "_id": "ac4bbc5f882264acadd04ccb5cc75b1c",
                                    "id": 136305,
                                    "type": "e_cnvi",
                                    "e": "我喜欢用弹性好的文具。",
                                    "p_cn": "wo xihuan yong tanxing hao de wenju.",
                                    "p": "wǒ xǐhuan yòng tánxìng hǎo de wénjù."
                                },
                                {
                                    "m": "Loại cao su này có độ đàn hồi rất mạnh.",
                                    "p_vn": "loai cao su nay co do dan hoi rat manh.",
                                    "_id": "ac4bbc5f882264acadd04ccb5cc769ef",
                                    "id": 136306,
                                    "type": "e_cnvi",
                                    "e": "这种橡胶材料有很强的弹性。",
                                    "p_cn": "zhe zhong xiangjiao cailiao you hen qiang de tanxing.",
                                    "p": "zhè zhǒng xiàngjiāo cáiliào yǒu hěn qiáng de tánxìng."
                                }
                            ]
                        }
                    ]
                },
                {
                    "kind": "adj",
                    "means": [
                        {
                            "mean": "linh hoạt, uyển chuyển",
                            "explain": "比喻对事物处理可以灵活的",
                            "examples": [
                                {
                                    "m": "Thời gian làm việc của chúng tôi rất linh hoạt.",
                                    "p_vn": "thoi gian lam viec cua chung toi rat linh hoat.",
                                    "_id": "ac4bbc5f882264acadd04ccb5cc77225",
                                    "id": 136307,
                                    "type": "e_cnvi",
                                    "e": "我们的工作时间很有弹性。",
                                    "p_cn": "women de gongzuo shijian hen you tanxing.",
                                    "p": "wǒmen de gōngzuò shíjiān hěn yǒu tánxìng."
                                },
                                {
                                    "m": "Kế hoạch của cô ấy được sắp xếp rất linh hoạt.",
                                    "p_vn": "ke hoach cua co ay duoc sap xep rat linh hoat.",
                                    "_id": "ac4bbc5f882264acadd04ccb5cc77649",
                                    "id": 136308,
                                    "type": "e_cnvi",
                                    "e": "她的计划安排得很有弹性。",
                                    "p_cn": "ta de jihua anpai de hen you tanxing.",
                                    "p": "tā de jìhuà ānpái dé hěn yǒu tánxìng."
                                },
                                {
                                    "m": "Lịch trình của dự án này rất linh hoạt.",
                                    "p_vn": "lich trinh cua du an nay rat linh hoat.",
                                    "_id": "ac4bbc5f882264acadd04ccb5cc776e6",
                                    "id": 136309,
                                    "type": "e_cnvi",
                                    "e": "这个项目的时间表很有弹性。",
                                    "p_cn": "zhege xiangmu di shijian biao hen you tanxing.",
                                    "p": "zhègè xiàngmù dì shíjiān biǎo hěn yǒu tánxìng."
                                },
                                {
                                    "m": "Cô ấy rất linh hoạt khi xử lý vấn đề.",
                                    "p_vn": "co ay rat linh hoat khi xu ly van de.",
                                    "_id": "ac4bbc5f882264acadd04ccb5cc77736",
                                    "id": 136310,
                                    "type": "e_cnvi",
                                    "e": "她处理问题时非常有弹性。",
                                    "p_cn": "ta chuli wenti shi feichang you tanxing.",
                                    "p": "tā chǔlǐ wèntí shí fēicháng yǒu tánxìng."
                                }
                            ]
                        }
                    ]
                }
            ],
            "popularity": {
                "notebook": 185,
                "search": 1867
            },
            "snym": {
                "syno": [
                    "韧性"
                ],
                "anto": [
                    "塑性"
                ]
            },
            "lv_hsk_new": "6, 7-9",
            "pinyin": "tánxìng",
            "cn_vi": "đàn tính",
            "word": "弹性",
            "id": 11171,
            "phonetic": "tanxing",
            "rank": 5924,
            "lv_tocfl": 5,
            "compound": null
        },
        {
            "measure": null,
            "zhuyin": "ㄉㄢˋㄔˋ",
            "_id": "036b824772914181bbe0d5eb2e9f583c",
            "type": "cnvi",
            "content": [
                {
                    "kind": "v",
                    "means": [
                        {
                            "mean": "buộc tội và chỉ trích",
                            "explain": "accuse and criticize",
                            "examples": []
                        }
                    ]
                }
            ],
            "popularity": {
                "notebook": 0,
                "search": 0
            },
            "snym": null,
            "cn_vi": "đạn xích",
            "pinyin": "dàn chì",
            "word": "弹斥",
            "id": 96526,
            "phonetic": "danchi",
            "rank": 158107,
            "kind": [
                "v"
            ],
            "compound": null
        },
        {
            "measure": null,
            "zhuyin": "ㄉㄢˋㄑㄧㄡˊ",
            "_id": "4f7e1947955c45d18a1890fe46da753c",
            "type": "cnvi",
            "content": [
                {
                    "kind": "v",
                    "means": [
                        {
                            "mean": "chơi bi",
                            "explain": "to play marbles",
                            "examples": []
                        }
                    ]
                }
            ],
            "popularity": {
                "notebook": 2,
                "search": 16
            },
            "snym": null,
            "cn_vi": "đạn cầu",
            "pinyin": "dàn qiú",
            "word": "弹球",
            "id": 96528,
            "phonetic": "danqiu",
            "rank": 89959,
            "kind": [
                "v"
            ],
            "compound": null
        },
        {
            "measure": null,
            "topic": "6, 18, 27, 43, 54",
            "zhuyin": "ㄅㄠˋㄉㄢˋ",
            "_id": "584779a627f2428a9ac6077ccf297901",
            "type": "cnvi",
            "content": [
                {
                    "kind": "n",
                    "means": [
                        {
                            "mean": "bom",
                            "explain": "bomb",
                            "examples": []
                        },
                        {
                            "mean": "nổ",
                            "explain": "explosion",
                            "examples": []
                        }
                    ]
                }
            ],
            "popularity": {
                "notebook": 0,
                "search": 14
            },
            "snym": null,
            "cn_vi": "bạo đạn",
            "pinyin": "bào dàn",
            "word": "爆弹",
            "id": 98332,
            "phonetic": "baodan",
            "rank": 94013,
            "kind": [
                "n"
            ],
            "compound": null
        },
        {
            "kind": [
                "n"
            ],
            "measure": null,
            "zhuyin": "ㄍㄨˇㄉㄢˋ",
            "_id": "7b265bcdbed6d52600b57e76864c1663",
            "type": "cnvi",
            "content": [
                {
                    "kind": "n",
                    "means": [
                        {
                            "mean": "bom cô-ban",
                            "explain": "一种理论上的原子弹或氢弹，装于钴壳内，爆炸后可使钴变成致命的放射性尘埃",
                            "examples": []
                        }
                    ]
                }
            ],
            "popularity": {
                "notebook": 0,
                "search": 2
            },
            "snym": null,
            "cn_vi": "cổ đạn",
            "pinyin": "gǔ dàn",
            "word": "钴弹",
            "id": 20483,
            "phonetic": "gudan",
            "rank": 141403,
            "lv_tocfl": null,
            "compound": null
        },
        {
            "measure": null,
            "topic": "",
            "_id": "5e0d37648f8d438eb4eef39a9d2fe525",
            "type": "cnvi",
            "content": [
                {
                    "kind": "n",
                    "means": [
                        {
                            "mean": "đạn giới",
                            "explain": "",
                            "examples": []
                        }
                    ]
                }
            ],
            "compare": null,
            "snym": null,
            "cn_vi": "đạn giới",
            "pinyin": "dàn jiè",
            "popularity": {
                "notebook": 0,
                "search": 0
            },
            "word": "弹界",
            "id": 177236,
            "phonetic": "danjie",
            "rank": 158107,
            "kind": [
                "n"
            ],
            "compound": null
        },
        {
            "kind": [
                "n"
            ],
            "measure": null,
            "zhuyin": "ㄉㄢˋㄊㄧˇ",
            "_id": "00a74d5f560c9121430697e30a3c9c4d",
            "type": "cnvi",
            "content": [
                {
                    "kind": "n",
                    "means": [
                        {
                            "mean": "thân đạn",
                            "explain": "作为炮弹主要部分的弹筒;特指炮弹的从定心提环到弹底导带那一部分",
                            "examples": []
                        }
                    ]
                }
            ],
            "popularity": {
                "notebook": 0,
                "search": 11
            },
            "snym": null,
            "cn_vi": "đạn thể",
            "pinyin": "dàn tǐ",
            "word": "弹体",
            "id": 11165,
            "phonetic": "danti",
            "rank": 99500,
            "lv_tocfl": null,
            "compound": null
        },
        {
            "kind": [
                "n"
            ],
            "measure": null,
            "topic": "18",
            "zhuyin": "ㄌㄧㄡˊㄉㄢˋ",
            "_id": "5be542a921572b1ceac1eea0b49490f0",
            "type": "cnvi",
            "content": [
                {
                    "kind": "n",
                    "means": [
                        {
                            "mean": "mảnh đạn; mảnh bom",
                            "explain": "一种依靠炸药爆炸后产生的碎片、冲击波来杀伤或摧毁目标的炮弹旧称开花弹",
                            "examples": [
                                {
                                    "m": "\"Một quả bom xịt bất ngờ phát nổ, sau đó là một cảnh hỗn loạn khiến tôi không biết phải làm gì.\"",
                                    "p_vn": "\"Mot qua bom xit bat ngo phat no, sau do la mot canh hon loan khien toi khong biet phai lam gi.\"",
                                    "_id": "f511cf3435e64fed8d4256e1fe862d54",
                                    "id": 71098,
                                    "type": "e_cnvi",
                                    "e": "＂一枚手榴弹意外地发生了爆炸，接着是一片混乱，使我不知所措。＂",
                                    "p_cn": "yi mei shouliudan yiwai di fasheng le baozha jiezhe shi yipian hunluan shi wo buzhisuocuo",
                                    "p": "yī méi shǒuliúdàn yìwài dì fāshēng le bàozhà jiēzhe shì yīpiàn hùnluàn shǐ wǒ bùzhīsuǒcuò"
                                }
                            ]
                        },
                        {
                            "mean": "lựu đạn",
                            "explain": "泛指手榴弹、花榴弹和用炮发射的榴弹",
                            "examples": []
                        }
                    ]
                }
            ],
            "popularity": {
                "notebook": 3,
                "search": 35
            },
            "snym": null,
            "cn_vi": "lựu đạn",
            "pinyin": "liúdàn",
            "word": "榴弹",
            "id": 35790,
            "phonetic": "liudan",
            "rank": 66920,
            "lv_tocfl": null,
            "compound": null
        },
        {
            "kind": [
                "n"
            ],
            "measure": null,
            "zhuyin": "ㄒㄧㄢˋㄉㄢˋ",
            "_id": "02217b482e1469fcd892e5e3e6b88e63",
            "type": "cnvi",
            "content": [
                {
                    "kind": "n",
                    "means": [
                        {
                            "mean": "đạn ria; đạn ghém; đạn trái phá; lựu pháo",
                            "explain": "炮弹的一种，弹壁薄，内装黑色炸药和小铅球或钢球，弹头装有定时的引信，能在预定的目标上空及其附近爆炸，杀伤敌军的密集人马也叫霰弹、子母弹、群子弹见〖榴 霰弹〗",
                            "examples": [
                                {
                                    "m": "Một vụ nổ súng ngắn?",
                                    "p_vn": "Mot vu no sung ngan?",
                                    "_id": "2f7b853253874ecbb0ba47b5d01dc4ec",
                                    "id": 61822,
                                    "type": "e_cnvi",
                                    "e": "用霰弹枪连杀两人",
                                    "p_cn": "yong xiandanqiang liansha liangren",
                                    "p": "yòng xiàndànqiāng liánshā liǎngrén"
                                },
                                {
                                    "m": "Omar nhận những phát súng ngắn.",
                                    "p_vn": "Omar nhan nhung phat sung ngan.",
                                    "_id": "512161a3ec2b41d1a0d5296535ca774c",
                                    "id": 61823,
                                    "type": "e_cnvi",
                                    "e": "Omar被霰弹枪击中",
                                    "p_cn": "omar bei xiandanqiang jizhong",
                                    "p": "Omar bèi xiàndànqiāng jízhōng"
                                }
                            ]
                        }
                    ]
                }
            ],
            "popularity": {
                "notebook": 0,
                "search": 11
            },
            "snym": null,
            "cn_vi": "tản đạn",
            "pinyin": "xiàndàn",
            "word": "霰弹",
            "id": 55255,
            "phonetic": "xiandan",
            "rank": 101285,
            "lv_tocfl": null,
            "compound": null
        },
        {
            "measure": null,
            "topic": "",
            "_id": "1cec132530ab40c38299411118bd8f35",
            "type": "cnvi",
            "content": [
                {
                    "kind": "v",
                    "means": [
                        {
                            "mean": "nẹt",
                            "explain": "",
                            "examples": [
                                {
                                    "m": "Con tàu chiến khổng lồ này đã bị một quả tên lửa tự động tìm đánh trúng.",
                                    "p_vn": "Con tau chien khong lo nay da bi mot qua ten lua tu dong tim danh trung.",
                                    "_id": "73c562046707431e856daa72b65eb205",
                                    "id": 72172,
                                    "type": "e_cnvi",
                                    "e": "这只巨大的军舰被一枚自动寻的导弹击中。",
                                    "p_cn": "zhe zhi juda de junjian bei yi mei zidong xundi daodan jizhong",
                                    "p": "zhè zhǐ jùdà de jūnjiàn bèi yī méi zìdòng xúndì dǎodàn jīzhòng"
                                }
                            ]
                        }
                    ]
                }
            ],
            "compare": null,
            "snym": null,
            "cn_vi": "đạn kích",
            "pinyin": "dàn jī",
            "popularity": {
                "notebook": 0,
                "search": 5
            },
            "word": "弹击",
            "id": 178596,
            "phonetic": "danji",
            "rank": 120814,
            "kind": [
                "v"
            ],
            "compound": null
        },
        {
            "kind": [
                "v"
            ],
            "measure": null,
            "zhuyin": "ㄉㄢˋㄏㄜˊ",
            "_id": "0ec02ec867dc3e2a89d8bd0b80b24228",
            "type": "cnvi",
            "content": [
                {
                    "kind": "v",
                    "means": [
                        {
                            "mean": "giám quan (quan chuyên giám sát vạch tội quan lại)",
                            "explain": "君主时代担任监察职务的官员检举官吏的罪状",
                            "examples": []
                        },
                        {
                            "mean": "tố cáo; vạch tội (quốc hội một số nước vạch tội những người cầm quyền)",
                            "explain": "某些国家的议会抨击政府工作人员，揭发其罪状",
                            "examples": []
                        },
                        {
                            "mean": "hặc",
                            "explain": "揭发罪状",
                            "examples": []
                        },
                        {
                            "mean": "đả kích; công kích",
                            "explain": "用评论来攻击 (某人或某种言论、行动)",
                            "examples": []
                        }
                    ]
                }
            ],
            "popularity": {
                "notebook": 7,
                "search": 137
            },
            "snym": {
                "syno": [
                    "毁谤"
                ],
                "anto": [
                    "赞扬",
                    "嘉奖"
                ]
            },
            "cn_vi": "đàn hặc",
            "pinyin": "tánhé",
            "word": "弹劾",
            "id": 11150,
            "phonetic": "tanhe",
            "rank": 35147,
            "lv_tocfl": null,
            "compound": null
        },
        {
            "kind": [
                "n"
            ],
            "measure": null,
            "zhuyin": "ㄆㄧㄥˊㄉㄢˋ",
            "_id": "0e570ed8e510ac7443cac9e68a1f5b89",
            "type": "cnvi",
            "content": [
                {
                    "kind": "n",
                    "means": [
                        {
                            "mean": "Bình đàn (một hình thức văn nghệ dân gian, vừa kể chuyện, vừa hát, vừa đàn, lưu hành ở vùng Giang Tô, Chiết Giang,Trung Quốc)",
                            "explain": "曲艺的一种，流行于江苏，浙江一带，有说有唱，由评话和弹词结合而成",
                            "examples": []
                        },
                        {
                            "mean": "bình thoại và đàn từ",
                            "explain": "评话和弹词的合称",
                            "examples": []
                        }
                    ]
                }
            ],
            "popularity": {
                "notebook": 1,
                "search": 46
            },
            "snym": null,
            "cn_vi": "bình đạn",
            "pinyin": "píngtán",
            "word": "评弹",
            "id": 41279,
            "phonetic": "pingtan",
            "rank": 59900,
            "lv_tocfl": null,
            "compound": null
        },
        {
            "measure": null,
            "topic": "6, 13, 15, 29, 68, 72",
            "zhuyin": "ㄓㄨㄥㄉㄢˋ",
            "_id": "5f8f1986594c4b6c9095c62eabe865ed",
            "type": "cnvi",
            "content": [
                {
                    "kind": "v",
                    "means": [
                        {
                            "mean": "trúng đạn",
                            "explain": "hit by a bullet",
                            "examples": [
                                {
                                    "m": "Tôi đã bị trúng đạn hai lần",
                                    "p_vn": "Toi da bi trung dan hai lan",
                                    "_id": "58dd0dac3c584d3e9b8bf7db1e37cead",
                                    "id": 58652,
                                    "type": "e_cnvi",
                                    "e": "小女子还真中弹过两次",
                                    "p_cn": "xiaonvzi huan zhen zhongdan guo liangci",
                                    "p": "xiǎonv̌zǐ huán zhēn zhōngdàn guò liǎngcì"
                                }
                            ]
                        },
                        {
                            "mean": "bắn",
                            "explain": "shot",
                            "examples": [
                                {
                                    "m": "Người đàn ông này đã bị bắn.",
                                    "p_vn": "Nguoi dan ong nay da bi ban.",
                                    "_id": "238b56d6abec47918a8dbc2fd7b9623d",
                                    "id": 58653,
                                    "type": "e_cnvi",
                                    "e": "这个人中弹了",
                                    "p_cn": "zhege ren zhongdan le",
                                    "p": "zhègè rén zhōngdàn le"
                                }
                            ]
                        }
                    ]
                }
            ],
            "popularity": {
                "notebook": 3,
                "search": 13
            },
            "snym": null,
            "cn_vi": "trung đạn",
            "pinyin": "zhòng dàn",
            "word": "中弹",
            "id": 106628,
            "phonetic": "zhongdan",
            "rank": 95373,
            "kind": [
                "v"
            ],
            "compound": null
        },
        {
            "measure": null,
            "zhuyin": "ㄉㄢˋㄕㄜˊ",
            "_id": "bc49d8880094447d8b5a7f215dd8e173",
            "type": "cnvi",
            "content": [
                {
                    "kind": "v",
                    "means": [
                        {
                            "mean": "mắc kẹt",
                            "explain": "to cluck",
                            "examples": []
                        },
                        {
                            "mean": "để lừa",
                            "explain": "to trill",
                            "examples": []
                        }
                    ]
                }
            ],
            "popularity": {
                "notebook": 2,
                "search": 94
            },
            "snym": null,
            "cn_vi": "đạn thiệt",
            "pinyin": "dàn shé",
            "word": "弹舌",
            "id": 96531,
            "phonetic": "danshe",
            "rank": 42922,
            "kind": [
                "v"
            ],
            "compound": null
        },
        {
            "kind": [
                "n"
            ],
            "measure": {
                "pinyin": "Lì, kē, fā",
                "examples": "子弹打中了靶子。\nZǐdàn dǎ zhòng le bǎzi.\nViên đạn đã tìm thấy dấu vết của nó.",
                "measure": "粒, 颗, 发"
            },
            "topic": "18",
            "zhuyin": "ㄗ˙ㄉㄢˋ",
            "_id": "e21042435234eaa1e5f453c4c184a708",
            "type": "cnvi",
            "content": [
                {
                    "kind": "n",
                    "means": [
                        {
                            "mean": "đạn; viên đạn",
                            "explain": "枪弹",
                            "examples": [
                                {
                                    "m": "Tháo đạn ra.",
                                    "p_vn": "thao dan ra.",
                                    "_id": "039d32e9621817310369c8ce97cb7a80",
                                    "id": 39791,
                                    "type": "e_cnvi",
                                    "e": "把子弹退出来。",
                                    "p_cn": "ba zidan tuichu lai。",
                                    "p": "bǎ zǐdàn tùichū lái。"
                                },
                                {
                                    "m": "một viên đạn.",
                                    "p_vn": "mot vien dan",
                                    "_id": "1b9e3ecc95835704c9a46fd00338fcaa",
                                    "id": 23235,
                                    "type": "e_cnvi",
                                    "e": "一颗子弹。",
                                    "p_cn": "yi ke zidan",
                                    "p": "yīkē zǐdàn。"
                                },
                                {
                                    "m": "đạn bay qua đầu vèo vèo.",
                                    "p_vn": "dan bay qua dau veo veo",
                                    "_id": "35abb5178736e73151bc8262ef82660a",
                                    "id": 36922,
                                    "type": "e_cnvi",
                                    "e": "子弹咝咝咝地从头顶上飞过。",
                                    "p_cn": "zidan si si si de cong touding shang feiguo",
                                    "p": "zǐdàn sī sī sī de cóng tóudǐng shàng fēiguò."
                                },
                                {
                                    "m": "Một viên đạn trong ngực anh ta.",
                                    "p_vn": "Mot vien dan trong nguc anh ta.",
                                    "_id": "4a962fb1ab3a42d2b6f45e2f5ac9cfcd",
                                    "id": 65225,
                                    "type": "e_cnvi",
                                    "e": "子弹击中胸部",
                                    "p_cn": "zidan jizhong xiongbu",
                                    "p": "zǐdàn jízhōng xiōngbù"
                                },
                                {
                                    "m": "một băng đạn.",
                                    "p_vn": "mot bang dan.",
                                    "_id": "4f9ec3f3c7fa8f972f6d08af2301ae86",
                                    "id": 30257,
                                    "type": "e_cnvi",
                                    "e": "一排子弹。",
                                    "p_cn": "yipai zidan。",
                                    "p": "yīpái zǐdàn。"
                                }
                            ]
                        }
                    ]
                }
            ],
            "popularity": {
                "notebook": 94,
                "search": 759
            },
            "snym": {
                "syno": [
                    "枪弹"
                ]
            },
            "lv_hsk_new": "5, 6",
            "pinyin": "zǐdàn",
            "cn_vi": "tử đạn",
            "word": "子弹",
            "id": 66618,
            "phonetic": "zidan",
            "rank": 12014,
            "lv_tocfl": 5,
            "compound": null
        },
        {
            "kind": [
                "v"
            ],
            "measure": null,
            "topic": "6, 19, 47, 58",
            "zhuyin": "ㄉㄢˋㄓˇ",
            "_id": "de2efd89895f927b9ade57c9129bed6b",
            "type": "cnvi",
            "content": [
                {
                    "kind": "v",
                    "means": [
                        {
                            "mean": "trong nháy mắt; loáng một cái",
                            "explain": "比喻时间极短暂",
                            "examples": [
                                {
                                    "m": "trong nháy mắt; trong chốc lát.",
                                    "p_vn": "trong nhay mat; trong choc lat",
                                    "_id": "af5e3dbacc734b53db7822d455951dc7",
                                    "id": 7087,
                                    "type": "e_cnvi",
                                    "e": "弹指之间",
                                    "p_cn": "tanzhi zhi jian",
                                    "p": "tánzhǐ zhī jiān"
                                },
                                {
                                    "m": "thời gian thắm thoát thoi đưa",
                                    "p_vn": "thoi gian tham thoat thoi dua",
                                    "_id": "ce1933370bf9ceee9f682da35db3046d",
                                    "id": 7088,
                                    "type": "e_cnvi",
                                    "e": "弹指光阴",
                                    "p_cn": "tanzhi guangyin",
                                    "p": "tánzhǐ guāngyīn"
                                }
                            ]
                        }
                    ]
                }
            ],
            "popularity": {
                "notebook": 7,
                "search": 125
            },
            "snym": null,
            "cn_vi": "đàn chỉ",
            "pinyin": "tánzhǐ",
            "word": "弹指",
            "id": 11175,
            "phonetic": "tanzhi",
            "rank": 37016,
            "lv_tocfl": null,
            "compound": null
        },
        {
            "measure": null,
            "zhuyin": "ㄉㄢˋㄅㄛ",
            "_id": "94ecc5a6c4454576ab3572f84d61a1b4",
            "type": "cnvi",
            "content": [
                {
                    "kind": "v",
                    "means": [
                        {
                            "mean": "nhổ (một chuỗi)",
                            "explain": "to pluck (a string)",
                            "examples": []
                        }
                    ]
                }
            ],
            "popularity": {
                "notebook": 1,
                "search": 34
            },
            "snym": null,
            "cn_vi": "đạn bát",
            "pinyin": "tánbō",
            "word": "弹拨",
            "id": 91260,
            "phonetic": "tanbo",
            "rank": 67711,
            "kind": [
                "v"
            ],
            "compound": null
        }
    ],
    "query": "弹"
}